CHANGES.rst
MANIFEST.in
README.rst
setup.cfg
setup.py
collective/__init__.py
collective.portlet.relateditems.egg-info/PKG-INFO
collective.portlet.relateditems.egg-info/SOURCES.txt
collective.portlet.relateditems.egg-info/dependency_links.txt
collective.portlet.relateditems.egg-info/entry_points.txt
collective.portlet.relateditems.egg-info/namespace_packages.txt
collective.portlet.relateditems.egg-info/not-zip-safe
collective.portlet.relateditems.egg-info/requires.txt
collective.portlet.relateditems.egg-info/top_level.txt
collective/portlet/__init__.py
collective/portlet/relateditems/__init__.py
collective/portlet/relateditems/configure.zcml
collective/portlet/relateditems/relateditems.pt
collective/portlet/relateditems/relateditems.py
collective/portlet/relateditems/usei18ndude.sh
collective/portlet/relateditems/version.txt
collective/portlet/relateditems/i18n/collective.portlet.relateditems-plone-cs.po
collective/portlet/relateditems/i18n/collective.portlet.relateditems-plone-da.po
collective/portlet/relateditems/i18n/collective.portlet.relateditems-plone-en.po
collective/portlet/relateditems/i18n/collective.portlet.relateditems-plone-nl.po
collective/portlet/relateditems/locales/collective.portlet.relateditems.pot
collective/portlet/relateditems/locales/cs/LC_MESSAGES/collective.portlet.relateditems.mo
collective/portlet/relateditems/locales/cs/LC_MESSAGES/collective.portlet.relateditems.po
collective/portlet/relateditems/locales/da/LC_MESSAGES/collective.portlet.relateditems.mo
collective/portlet/relateditems/locales/da/LC_MESSAGES/collective.portlet.relateditems.po
collective/portlet/relateditems/locales/en/LC_MESSAGES/collective.portlet.relateditems.mo
collective/portlet/relateditems/locales/en/LC_MESSAGES/collective.portlet.relateditems.po
collective/portlet/relateditems/locales/nl/LC_MESSAGES/collective.portlet.relateditems.mo
collective/portlet/relateditems/locales/nl/LC_MESSAGES/collective.portlet.relateditems.po
collective/portlet/relateditems/plonelocales/plone.pot
collective/portlet/relateditems/plonelocales/cs/LC_MESSAGES/plone.mo
collective/portlet/relateditems/plonelocales/cs/LC_MESSAGES/plone.po
collective/portlet/relateditems/plonelocales/da/LC_MESSAGES/plone.mo
collective/portlet/relateditems/plonelocales/da/LC_MESSAGES/plone.po
collective/portlet/relateditems/plonelocales/en/LC_MESSAGES/plone.mo
collective/portlet/relateditems/plonelocales/en/LC_MESSAGES/plone.po
