Metadata-Version: 1.1
Name: collective.portlet.relateditems
Version: 0.3.11
Summary: A Plone portlet to display similar items to context
Home-page: https://github.com/collective/collective.portlet.relateditems
Author: Rui Guerra, kiorky
Author-email: rui AT v2 DOT nl, kiorky <kiorky@cryptelium.net>, David Jonas <david@intk.com>
License: GPL
Keywords: related,categories,keywords
Platform: UNKNOWN
Classifier: Framework :: Plone
Classifier: Framework :: Plone :: 4.2
Classifier: Framework :: Plone :: 4.3
Classifier: Framework :: Plone
Classifier: Framework :: Zope2
Classifier: Framework :: Zope3
Classifier: Programming Language :: Python
Classifier: Programming Language :: Python :: 2.6
Classifier: Programming Language :: Python :: 2.7
Classifier: Topic :: Software Development :: Libraries :: Python Modules
